{
	"id": "3f82363c-ba70-4705-8b70-58b57e7d9d37",
	"name": "DevHttp",
	"values": [
		{
			"key": "userId",
			"value": "1",
			"type": "default",
			"enabled": true
		},
		{
			"key": "apiKeyId",
			"value": "2",
			"type": "default",
			"enabled": true
		},
		{
			"key": "keystoreId",
			"value": "3",
			"type": "default",
			"enabled": true
		},
		{
			"key": "secretId",
			"value": "4",
			"type": "default",
			"enabled": true
		},
		{
			"key": "adminUserId",
			"value": "?",
			"type": "any",
			"enabled": true
		},
		{
			"key": "firstUserId",
			"value": "",
			"type": "any",
			"enabled": true
		},
		{
			"key": "announcementId",
			"value": "",
			"type": "any",
			"enabled": true
		},
		{
			"key": "test_user",
			"value": "szrpet",
			"type": "default",
			"enabled": true
		},
		{
			"key": "test_pass",
			"value": "Asdf1234",
			"type": "default",
			"enabled": true
		},
		{
			"key": "promptFailure",
			"value": "",
			"type": "any",
			"enabled": true
		},
		{
			"key": "host_url",
			"value": "http://localhost:8080",
			"type": "default",
			"enabled": true
		},
		{
			"key": "deletableUserId",
			"value": "",
			"type": "any",
			"enabled": true
		}
	],
	"_postman_variable_scope": "environment",
	"_postman_exported_at": "2024-09-13T08:58:46.332Z",
	"_postman_exported_using": "Postman/11.12.0"
}